{
	"data": {
		"users": {
			"0": {
				"id": 1,
				"firstname": "Eloy",
				"lastname": "Rowe",
				"thumbnail": "https://cdn.fakercloud.com/avatars/bruno_mart_128.jpg",
				"email": "Krystel_Johnson5@example.com",
				"password": "Uriel_Leuschke@gmail.com",
				"created_at": "2022-04-28T09:56:41.623Z"
			},
			"1": {
				"id": 2,
				"firstname": "Ansel",
				"lastname": "Brown",
				"thumbnail": "https://cdn.fakercloud.com/avatars/jedbridges_128.jpg",
				"email": "Mortimer_Effertz24@example.org",
				"password": "Dedrick_Bartoletti@hotmail.com",
				"created_at": "2022-04-28T13:48:18.624Z"
			},
			"2": {
				"id": 3,
				"firstname": "Jarrod",
				"lastname": "Sipes",
				"thumbnail": "https://cdn.fakercloud.com/avatars/byrnecore_128.jpg",
				"email": "Triston.Fadel37@example.org",
				"password": "Mary_Smith@gmail.com",
				"created_at": "2022-04-29T07:16:14.005Z"
			},
			"3": {
				"id": 4,
				"firstname": "Wanda",
				"lastname": "Mertz",
				"thumbnail": "https://cdn.fakercloud.com/avatars/petar_prog_128.jpg",
				"email": "Ebony70@example.com",
				"password": "Carmine61@hotmail.com",
				"created_at": "2022-04-28T13:56:04.340Z"
			},
			"4": {
				"id": 5,
				"firstname": "Jarod",
				"lastname": "Roberts",
				"thumbnail": "https://cdn.fakercloud.com/avatars/ivanfilipovbg_128.jpg",
				"email": "Danyka7@example.com",
				"password": "Floyd49@hotmail.com",
				"created_at": "2022-04-29T03:11:11.858Z"
			},
			"5": {
				"id": 6,
				"firstname": "Francesca",
				"lastname": "Jenkins",
				"thumbnail": "https://cdn.fakercloud.com/avatars/vj_demien_128.jpg",
				"email": "Jacklyn42@example.com",
				"password": "Leora.Donnelly44@hotmail.com",
				"created_at": "2022-04-29T05:48:22.169Z"
			},
			"6": {
				"id": 7,
				"firstname": "Melyssa",
				"lastname": "Torphy",
				"thumbnail": "https://cdn.fakercloud.com/avatars/matkins_128.jpg",
				"email": "Rex86@example.org",
				"password": "Katlyn.Effertz@hotmail.com",
				"created_at": "2022-04-29T01:50:31.173Z"
			},
			"7": {
				"id": 8,
				"firstname": "Tony",
				"lastname": "Bailey",
				"thumbnail": "https://cdn.fakercloud.com/avatars/markolschesky_128.jpg",
				"email": "Ebba20@example.net",
				"password": "Antonia.Casper87@yahoo.com",
				"created_at": "2022-04-29T03:25:16.402Z"
			},
			"8": {
				"id": 9,
				"firstname": "Avery",
				"lastname": "Kuhn",
				"thumbnail": "https://cdn.fakercloud.com/avatars/wtrsld_128.jpg",
				"email": "Jon.Cremin45@example.com",
				"password": "Keshaun_Windler14@hotmail.com",
				"created_at": "2022-04-28T18:51:08.261Z"
			},
			"9": {
				"id": 10,
				"firstname": "Nettie",
				"lastname": "Torphy",
				"thumbnail": "https://cdn.fakercloud.com/avatars/rikas_128.jpg",
				"email": "Conner66@example.net",
				"password": "Kip.Beier48@gmail.com",
				"created_at": "2022-04-29T01:52:15.058Z"
			}
		},
		"campaigns": {
			"0": {
				"id": 1,
				"title": "seize efficient vortals",
				"thumbnail": "http://placeimg.com/640/480/people",
				"currentAmount": "32727.86",
				"goalAmount": "100000.00",
				"duration": "2022-09-07T14:55:00.229Z",
				"description": "Extended multi-tasking ability",
				"location": "Wallis and Futuna",
				"comments": {
					"length": 10,
					"comments": [
						{
							"id": 1,
							"content": "Assistant Investor Mexico tertiary fuchsia Automotive Shirt Dollar Bedfordshire Future compress Account Jewelery didactic Toys transmitter Vermont Market Small Gloves Squares AGP experiences Automotive users Orchestrator connecting Ports HTTP Auto",
							"user": {
								"firstname": "Woodrow",
								"lastname": "Luettgen",
								"thumbnail": "https://cdn.fakercloud.com/avatars/commadelimited_128.jpg",
								"email": "Clarissa.Osinski@example.com",
								"password": "Michaela.Kuhn29@yahoo.com",
								"created_at": "2022-04-29T07:15:43.711Z"
							}
						},
						{
							"id": 2,
							"content": "matrix Station functionalities toolset navigating Engineer framework Creative auxiliary Western mobile Ville generation Cambridgeshire Card Cook efficient bleeding-edge Solutions Nevada Computer Chips extend Switchable Account Markets zero Manager intuitive Tala",
							"user": {
								"firstname": "Emmitt",
								"lastname": "Langworth",
								"thumbnail": "https://cdn.fakercloud.com/avatars/helderleal_128.jpg",
								"email": "Telly76@example.org",
								"password": "Garfield9@gmail.com",
								"created_at": "2022-04-28T16:47:24.028Z"
							}
						},
						{
							"id": 3,
							"content": "Automotive FTP Ergonomic transmitter Bedfordshire payment Peso Electronics Buckinghamshire auxiliary monitoring Croatia Health Profit-focused Oval Practical Berkshire Taka calculating synthesize turquoise full-range payment Avon Georgia Program generate COM plum Generic",
							"user": {
								"firstname": "Brett",
								"lastname": "Gislason",
								"thumbnail": "https://cdn.fakercloud.com/avatars/rdsaunders_128.jpg",
								"email": "Angela.Stanton@example.com",
								"password": "Keanu_DuBuque@yahoo.com",
								"created_at": "2022-04-28T15:51:31.499Z"
							}
						},
						{
							"id": 4,
							"content": "Qatar Kroon Bedfordshire deposit Rupee panel web-enabled Virginia Account Buckinghamshire programming cyan implement protocol Fundamental Jewelery Sausages Sports Intelligent Islands synergies customized Plastic initiatives Fully-configurable extranet viral Maryland Virginia Intelligent",
							"user": {
								"firstname": "Robbie",
								"lastname": "Zboncak",
								"thumbnail": "https://cdn.fakercloud.com/avatars/iamgarth_128.jpg",
								"email": "Beth.Reilly17@example.org",
								"password": "Ramona.Batz@hotmail.com",
								"created_at": "2022-04-28T21:23:38.642Z"
							}
						},
						{
							"id": 5,
							"content": "success Chair success payment Wooden olive partnerships backing frame Rustic Tools invoice redundant intuitive Representative hack redundant violet engineer dedicated analyzer Iowa Unbranded benchmark payment Mission Orchestrator International Fundamental capacitor",
							"user": {
								"firstname": "Derrick",
								"lastname": "Christiansen",
								"thumbnail": "https://cdn.fakercloud.com/avatars/charlesrpratt_128.jpg",
								"email": "Ismael.Hudson70@example.net",
								"password": "Selina.Labadie27@yahoo.com",
								"created_at": "2022-04-29T07:18:39.303Z"
							}
						},
						{
							"id": 6,
							"content": "Account Benin input magenta extensible interfaces optical EXE Sleek Granite white purple Soft uniform local Mission generating Gloves Mississippi Plains intangible cross-platform calculating solutions Avon Mandatory withdrawal robust 24/7 Norfolk",
							"user": {
								"firstname": "Summer",
								"lastname": "Nolan",
								"thumbnail": "https://cdn.fakercloud.com/avatars/joelcipriano_128.jpg",
								"email": "Golden.Green@example.com",
								"password": "Dejon_Hane78@yahoo.com",
								"created_at": "2022-04-28T20:29:14.925Z"
							}
						},
						{
							"id": 7,
							"content": "hack Towels Moldova Generic Sausages Drives Idaho Handmade Rustic Concrete value-added Planner Land Hill bandwidth deliverables Wooden Village View Plaza Administrator HDD program yellow Plastic deposit Gorgeous Sleek Shirt killer",
							"user": {
								"firstname": "Julian",
								"lastname": "Metz",
								"thumbnail": "https://cdn.fakercloud.com/avatars/ariffsetiawan_128.jpg",
								"email": "Judd_Grimes@example.net",
								"password": "Douglas_Heller@hotmail.com",
								"created_at": "2022-04-28T15:08:57.127Z"
							}
						},
						{
							"id": 8,
							"content": "Program SSL e-business connecting convergence Meadows Gorgeous Salad Account China Facilitator Buckinghamshire and South rich revolutionize Afghani 60 maroon parsing expedite Grocery productize Handcrafted Mews up Dram Fresh deposit Money",
							"user": {
								"firstname": "Koby",
								"lastname": "Crooks",
								"thumbnail": "https://cdn.fakercloud.com/avatars/ssiskind_128.jpg",
								"email": "Lloyd84@example.net",
								"password": "Myriam.Nicolas@yahoo.com",
								"created_at": "2022-04-29T02:13:21.054Z"
							}
						},
						{
							"id": 9,
							"content": "yellow Stand-alone mindshare back-end Small Berkshire Peso withdrawal navigate Coordinator Liaison Branding Plastic Computers Fall Metrics Kazakhstan Account local PNG tangible Granite Savings task-force Director parsing Progressive Ergonomic transmitting invoice",
							"user": {
								"firstname": "Sunny",
								"lastname": "Parker",
								"thumbnail": "https://cdn.fakercloud.com/avatars/mutlu82_128.jpg",
								"email": "Chad12@example.com",
								"password": "Keegan.Jacobi@yahoo.com",
								"created_at": "2022-04-29T05:19:42.664Z"
							}
						},
						{
							"id": 10,
							"content": "Fish functionalities Cheese backing tan Gorgeous Sleek incremental monitor USB Garden Kentucky applications Steel motivating withdrawal Liaison deposit Oklahoma engage Ergonomic withdrawal New SDD Denar Focused Accountability Future-proofed motivating Gloves",
							"user": {
								"firstname": "Idella",
								"lastname": "Streich",
								"thumbnail": "https://cdn.fakercloud.com/avatars/nitinhayaran_128.jpg",
								"email": "America81@example.com",
								"password": "Kristin_Schuppe95@yahoo.com",
								"created_at": "2022-04-28T17:39:09.009Z"
							}
						}
					]
				}
			},
			"1": {
				"id": 2,
				"title": "revolutionize viral methodologies",
				"thumbnail": "http://placeimg.com/640/480/people",
				"currentAmount": "25170.00",
				"goalAmount": "100000.00",
				"duration": "2023-04-23T19:37:56.661Z",
				"description": "Networked optimal intranet",
				"location": "Cameroon",
				"comments": {
					"length": 10,
					"comments": [
						{
							"id": 1,
							"content": "conglomeration orchid area Operative deposit Borders vortals Assimilated Shoes bandwidth Producer SSL Cheese Viaduct bypassing bus Baby Agent Customer Wooden Account Account Plastic gold drive THX alarm withdrawal next-generation payment",
							"user": {
								"firstname": "Forrest",
								"lastname": "Willms",
								"thumbnail": "https://cdn.fakercloud.com/avatars/wikiziner_128.jpg",
								"email": "Yvonne_Maggio87@example.com",
								"password": "Jacynthe64@gmail.com",
								"created_at": "2022-04-28T18:34:50.355Z"
							}
						},
						{
							"id": 2,
							"content": "infomediaries Producer Distributed HDD Industrial virtual monitor Buckinghamshire Refined Awesome Malaysia internet port Granite productize deposit panel Somoni payment Bedfordshire Metal azure e-commerce Executive mesh primary payment efficient Hawaii Account",
							"user": {
								"firstname": "Brian",
								"lastname": "Bergnaum",
								"thumbnail": "https://cdn.fakercloud.com/avatars/hafeeskhan_128.jpg",
								"email": "Earnest.Keeling@example.com",
								"password": "Alvah.Stiedemann@gmail.com",
								"created_at": "2022-04-28T14:35:59.602Z"
							}
						},
						{
							"id": 3,
							"content": "Universal Rhode scalable analyzing secondary Handmade optimal Metal primary e-business Keys bricks-and-clicks best-of-breed Borders brand copying Direct Bike Interactions Loan Soft Avon Money leverage Optimized Rubber zero Administrator Mountains overriding",
							"user": {
								"firstname": "Manuela",
								"lastname": "Dooley",
								"thumbnail": "https://cdn.fakercloud.com/avatars/yesmeck_128.jpg",
								"email": "Gisselle_Hansen@example.net",
								"password": "Jayde43@hotmail.com",
								"created_at": "2022-04-28T21:10:15.658Z"
							}
						},
						{
							"id": 4,
							"content": "index demand-driven Innovative incubate synergize connecting Total solution haptic generating Architect Expanded Hat alarm edge Unbranded evolve Infrastructure intranet schemas Forward Cedi Graphic port Terrace Frozen teal bluetooth auxiliary Central",
							"user": {
								"firstname": "Asia",
								"lastname": "Prosacco",
								"thumbnail": "https://cdn.fakercloud.com/avatars/netonet_il_128.jpg",
								"email": "Adelia.Morissette24@example.com",
								"password": "Dangelo.Cronin@gmail.com",
								"created_at": "2022-04-29T04:15:43.046Z"
							}
						},
						{
							"id": 5,
							"content": "Regional Arkansas human-resource fresh-thinking e-markets service-desk mission-critical grow vertical JBOD Engineer IB white blue Ramp Officer RSS Bedfordshire convergence Bedfordshire generate Cotton Chicken Mobility TCP Cotton local Plastic redundant COM",
							"user": {
								"firstname": "Hadley",
								"lastname": "Walker",
								"thumbnail": "https://cdn.fakercloud.com/avatars/victorquinn_128.jpg",
								"email": "Daren_Bartell@example.org",
								"password": "Norval_Jacobson54@yahoo.com",
								"created_at": "2022-04-28T18:49:13.589Z"
							}
						},
						{
							"id": 6,
							"content": "Central Inverse Shilling Wooden Ameliorated Metal RAM Hills Nevada metrics Garden Borders Hat Soft overriding Ohio indigo Circles Corporate Market Health Credit Cambridgeshire Principal Handmade Manager Towels Grocery reboot Program",
							"user": {
								"firstname": "Uriel",
								"lastname": "Bogisich",
								"thumbnail": "https://cdn.fakercloud.com/avatars/karlkanall_128.jpg",
								"email": "Annabelle_Wiegand@example.net",
								"password": "Jeramy7@hotmail.com",
								"created_at": "2022-04-29T00:47:26.070Z"
							}
						},
						{
							"id": 7,
							"content": "Mexico Swaziland Assurance Coordinator mindshare attitude Licensed Borders and compressing Small IB Club Loan Accountability Pants Checking Wooden payment Carolina Factors Soft Computer Kina Belgium incentivize user-facing override executive Human",
							"user": {
								"firstname": "Javier",
								"lastname": "Kiehn",
								"thumbnail": "https://cdn.fakercloud.com/avatars/imsoper_128.jpg",
								"email": "Oceane_VonRueden@example.net",
								"password": "Sage_Corkery54@yahoo.com",
								"created_at": "2022-04-28T16:41:15.291Z"
							}
						},
						{
							"id": 8,
							"content": "Senior access Fundamental Hat scalable SQL generation Texas Gloves Avon Avon Supervisor invoice Chair Savings AI Colorado Technician deliverables hack Extension Ball Krona Malaysian Soap Massachusetts Account Assurance USB orange",
							"user": {
								"firstname": "Robert",
								"lastname": "Huel",
								"thumbnail": "https://cdn.fakercloud.com/avatars/keryilmaz_128.jpg",
								"email": "Shawn.Hammes@example.com",
								"password": "Saige_Jaskolski@gmail.com",
								"created_at": "2022-04-28T12:08:52.869Z"
							}
						},
						{
							"id": 9,
							"content": "context-sensitive plum Optimization withdrawal Account Fantastic Toys Borders Salad Mouse card Grenada syndicate redundant Armenia Wooden Garden programming Facilitator system payment Mountains multi-byte extensible deliverables Toys Steel Towels Investment programming",
							"user": {
								"firstname": "Marilou",
								"lastname": "Kemmer",
								"thumbnail": "https://cdn.fakercloud.com/avatars/ashernatali_128.jpg",
								"email": "Helga.Mills29@example.net",
								"password": "Loma_Hansen@hotmail.com",
								"created_at": "2022-04-28T23:11:12.837Z"
							}
						},
						{
							"id": 10,
							"content": "loyalty Global Jamaican next-generation Supervisor iterate interfaces Circles Operations sensor Bedfordshire Lesotho Wooden bandwidth SMS radical payment Senior impactful overriding matrices Tuna Assimilated strategic Orchestrator synthesizing lime Automotive Product e-services",
							"user": {
								"firstname": "Syble",
								"lastname": "Larkin",
								"thumbnail": "https://cdn.fakercloud.com/avatars/edgarchris99_128.jpg",
								"email": "Brett_Satterfield14@example.org",
								"password": "Teresa_Hudson38@yahoo.com",
								"created_at": "2022-04-28T22:00:17.618Z"
							}
						}
					]
				}
			},
			"2": {
				"id": 3,
				"title": "e-enable value-added portals",
				"thumbnail": "http://placeimg.com/640/480/people",
				"currentAmount": "22953.08",
				"goalAmount": "100000.00",
				"duration": "2022-05-15T14:52:39.256Z",
				"description": "Diverse client-server solution",
				"location": "China",
				"comments": {
					"length": 10,
					"comments": [
						{
							"id": 1,
							"content": "Wooden Avon matrix drive Games data-warehouse Texas Tactics Savings Reduced Associate bypassing proactive copying Lodge Cheese success Guyana regional Fresh Tasty even-keeled Shoes online Lead withdrawal system Outdoors Nebraska Central",
							"user": {
								"firstname": "Elyssa",
								"lastname": "Schiller",
								"thumbnail": "https://cdn.fakercloud.com/avatars/jnmnrd_128.jpg",
								"email": "Thea48@example.org",
								"password": "Alyson.Fahey@gmail.com",
								"created_at": "2022-04-29T01:25:26.797Z"
							}
						},
						{
							"id": 2,
							"content": "Grocery Iowa architect driver Granite payment Sleek circuit Coordinator Market Lithuania calculating Innovative deliver hacking application Dynamic cutting-edge Flat JSON Cambridgeshire structure Wooden Shoes Interactions Sleek Personal Utah customized transparent",
							"user": {
								"firstname": "Annabelle",
								"lastname": "Jerde",
								"thumbnail": "https://cdn.fakercloud.com/avatars/bu7921_128.jpg",
								"email": "Fermin.Wolf28@example.org",
								"password": "Ole.Kuhlman@gmail.com",
								"created_at": "2022-04-28T11:32:30.756Z"
							}
						},
						{
							"id": 3,
							"content": "Credit Accounts transmit invoice bandwidth circuit extend integrate revolutionary Account deposit Research cross-platform Avon parsing Licensed Generic Car strategize fault-tolerant parse Identity National Assistant backing cross-platform Credit Unbranded Functionality Delaware",
							"user": {
								"firstname": "Geovany",
								"lastname": "Terry",
								"thumbnail": "https://cdn.fakercloud.com/avatars/adellecharles_128.jpg",
								"email": "Lila_Lang@example.net",
								"password": "Maxie_McGlynn@yahoo.com",
								"created_at": "2022-04-28T21:20:08.202Z"
							}
						},
						{
							"id": 4,
							"content": "Niue Customer-focused maroon salmon mesh hack parse Baby Strategist Integration Awesome National Dinar Rupee payment Dynamic customized Optimization bluetooth drive value-added payment Account Coordinator e-commerce Computer cross-platform Officer parse world-class",
							"user": {
								"firstname": "Emery",
								"lastname": "Kohler",
								"thumbnail": "https://cdn.fakercloud.com/avatars/joreira_128.jpg",
								"email": "Eusebio4@example.com",
								"password": "Billy52@yahoo.com",
								"created_at": "2022-04-28T09:52:31.360Z"
							}
						},
						{
							"id": 5,
							"content": "calculating optical Carolina Concrete flexibility bypassing expedite payment Multi-tiered Mouse Customizable Cross-group Manager Concrete De-engineered grey Berkshire Account engineer Outdoors bypassing Bike Concrete Pierre Metal West enterprise Savings Automotive Tonga",
							"user": {
								"firstname": "Kadin",
								"lastname": "Dickens",
								"thumbnail": "https://cdn.fakercloud.com/avatars/markjenkins_128.jpg",
								"email": "Madilyn_Thompson66@example.com",
								"password": "Leland29@yahoo.com",
								"created_at": "2022-04-28T20:27:00.144Z"
							}
						},
						{
							"id": 6,
							"content": "Bridge invoice driver Jersey redundant override backing Berkshire Supervisor base feed Ecuador JBOD transmitter Proactive grow Granite Response Frozen enterprise Dollar Architect Concrete productize Home indigo monitoring program Nigeria proactive",
							"user": {
								"firstname": "Arturo",
								"lastname": "Auer",
								"thumbnail": "https://cdn.fakercloud.com/avatars/joreira_128.jpg",
								"email": "Lauryn.Walker@example.net",
								"password": "Amber32@gmail.com",
								"created_at": "2022-04-29T08:45:24.014Z"
							}
						},
						{
							"id": 7,
							"content": "Connecticut Optimization Cotton Optimized Enterprise-wide SAS Incredible withdrawal Regional Refined Florida Brand Nepal Cheese Cotton Ergonomic interface Profit-focused B2B payment interfaces Steel Avon Fully-configurable JSON Intelligent Saudi Designer Fresh withdrawal",
							"user": {
								"firstname": "Lera",
								"lastname": "Carter",
								"thumbnail": "https://cdn.fakercloud.com/avatars/sandywoodruff_128.jpg",
								"email": "Jake10@example.org",
								"password": "Stanford_Bartell46@hotmail.com",
								"created_at": "2022-04-28T17:30:57.311Z"
							}
						},
						{
							"id": 8,
							"content": "Handcrafted Pizza bandwidth-monitored Utah compressing niches bypassing Grocery Keyboard schemas eco-centric monitor Rapids copy Malaysia Rustic Product neural Rupee Dollar Table mobile Architect Keyboard olive flexibility invoice payment copy website",
							"user": {
								"firstname": "Timothy",
								"lastname": "Gutkowski",
								"thumbnail": "https://cdn.fakercloud.com/avatars/kumarrajan12123_128.jpg",
								"email": "Olaf.Hudson@example.com",
								"password": "Ana.Schmeler@yahoo.com",
								"created_at": "2022-04-29T01:10:03.299Z"
							}
						},
						{
							"id": 9,
							"content": "Chips Licensed Garden Bacon Usability Checking Card Small Paradigm sensor Rica array primary Steel Borders Interactions HTTP Sports Concrete yellow communities Franc ivory Bedfordshire alliance Idaho Markets Pizza port Account",
							"user": {
								"firstname": "Waldo",
								"lastname": "Gutmann",
								"thumbnail": "https://cdn.fakercloud.com/avatars/mbilderbach_128.jpg",
								"email": "Alfonzo15@example.org",
								"password": "Jarrett.Yundt12@hotmail.com",
								"created_at": "2022-04-29T00:07:29.336Z"
							}
						},
						{
							"id": 10,
							"content": "networks silver platforms Wooden systems overriding streamline access Cambridgeshire Pants Bouvet deposit Pizza Account New Wisconsin Wells Specialist Handmade redundant online Samoa Wooden Vision-oriented collaborative Electronics circuit Handcrafted Georgia and",
							"user": {
								"firstname": "Savion",
								"lastname": "Krajcik",
								"thumbnail": "https://cdn.fakercloud.com/avatars/anasnakawa_128.jpg",
								"email": "Brett_Franecki66@example.com",
								"password": "Burley.Kreiger44@gmail.com",
								"created_at": "2022-04-28T23:15:53.546Z"
							}
						}
					]
				}
			},
			"3": {
				"id": 4,
				"title": "synthesize cross-media action-items",
				"thumbnail": "http://placeimg.com/640/480/people",
				"currentAmount": "27037.79",
				"goalAmount": "100000.00",
				"duration": "2022-09-11T21:43:23.837Z",
				"description": "Horizontal dynamic paradigm",
				"location": "Nepal",
				"comments": {
					"length": 10,
					"comments": [
						{
							"id": 1,
							"content": "orange back Credit plum Card ADP silver Open-source Grocery SMTP Bedfordshire paradigms Island HTTP monetize wireless Factors Future Cambridgeshire magenta Towels Rubber Intelligent Peso Ergonomic Colorado Buckinghamshire hard withdrawal synthesize",
							"user": {
								"firstname": "Daniella",
								"lastname": "Zieme",
								"thumbnail": "https://cdn.fakercloud.com/avatars/miguelkooreman_128.jpg",
								"email": "Denis.Weber29@example.org",
								"password": "Vaughn.Will72@hotmail.com",
								"created_at": "2022-04-28T17:14:33.914Z"
							}
						},
						{
							"id": 2,
							"content": "niches Maldives strategize turquoise applications Missouri payment Handmade Books Generic Grass-roots mint SCSI intuitive Shirt withdrawal redefine generating Frozen Frozen Lights Cambridgeshire transform Executive Frozen Markets cohesive cross-platform robust Future",
							"user": {
								"firstname": "Adrienne",
								"lastname": "Howe",
								"thumbnail": "https://cdn.fakercloud.com/avatars/martip07_128.jpg",
								"email": "Geovany_Hartmann91@example.com",
								"password": "Mara_Mann71@gmail.com",
								"created_at": "2022-04-29T05:32:07.595Z"
							}
						},
						{
							"id": 3,
							"content": "bi-directional budgetary Auto ivory Lesotho Account repurpose Account seize reintermediate Norway back-end azure Credit Cocos Cook Specialist SMTP 24/7 Accountability B2B Web transmit approach program Colombian methodologies Shoes Account Bedfordshire",
							"user": {
								"firstname": "Zoe",
								"lastname": "Murazik",
								"thumbnail": "https://cdn.fakercloud.com/avatars/VinThomas_128.jpg",
								"email": "Shaina_Gerlach94@example.org",
								"password": "Barry_Beahan85@yahoo.com",
								"created_at": "2022-04-29T09:07:40.768Z"
							}
						},
						{
							"id": 4,
							"content": "override Metal Stream clear-thinking Rupee Interactions Fords face Lane ADP Rubber deposit Streamlined Hat lime Principal withdrawal Principal bypassing open-source scalable cross-media Unbranded azure Supervisor payment client-driven Djibouti Republic Expanded",
							"user": {
								"firstname": "Roma",
								"lastname": "Wehner",
								"thumbnail": "https://cdn.fakercloud.com/avatars/orkuncaylar_128.jpg",
								"email": "Donald74@example.com",
								"password": "Torrey.Flatley@gmail.com",
								"created_at": "2022-04-29T01:04:08.125Z"
							}
						},
						{
							"id": 5,
							"content": "hack generating Borders connect Illinois Toys Account content-based Berkshire Handcrafted mobile circuit Peso Loan Forint Massachusetts Tools International Directives revolutionize hacking Plastic French Berkshire national Health markets streamline Streamlined Checking",
							"user": {
								"firstname": "Noelia",
								"lastname": "Toy",
								"thumbnail": "https://cdn.fakercloud.com/avatars/hjartstrorn_128.jpg",
								"email": "Toney62@example.org",
								"password": "Izaiah_Veum50@gmail.com",
								"created_at": "2022-04-29T05:06:15.990Z"
							}
						},
						{
							"id": 6,
							"content": "Borders synthesize Books JSON non-volatile Berkshire Cambridgeshire Savings indigo e-business Proactive one-to-one Web Investment Borders 1080p Clothing Heights Gloves Principal up bandwidth Borders intermediate Strategist Operative microchip aggregate Reduced Loan",
							"user": {
								"firstname": "Efrain",
								"lastname": "Kris",
								"thumbnail": "https://cdn.fakercloud.com/avatars/thomasschrijer_128.jpg",
								"email": "Deja.Wisozk@example.com",
								"password": "Madisyn.Rolfson96@gmail.com",
								"created_at": "2022-04-28T12:11:02.331Z"
							}
						},
						{
							"id": 7,
							"content": "Triple-buffered dynamic open-source Marketing cross-media bandwidth end-to-end redundant web granular synthesize Mouse Nepalese revolutionary Taka Vista blue Buckinghamshire sensor Facilitator structure Island Tala Avon Plastic Communications e-tailers Cross-platform Officer Customer",
							"user": {
								"firstname": "Yoshiko",
								"lastname": "Crist",
								"thumbnail": "https://cdn.fakercloud.com/avatars/carlyson_128.jpg",
								"email": "Tate.Nicolas@example.org",
								"password": "Matilde_Mueller@hotmail.com",
								"created_at": "2022-04-28T22:45:10.016Z"
							}
						},
						{
							"id": 8,
							"content": "online Sierra interactive Isle matrix 24/365 Planner Maryland Shoes analyzing Villages Metal Tugrik array India Fantastic Crescent Designer Progressive South Chips secured calculating Soft users infrastructure Oro synthesizing compress Operative",
							"user": {
								"firstname": "Idell",
								"lastname": "Orn",
								"thumbnail": "https://cdn.fakercloud.com/avatars/marciotoledo_128.jpg",
								"email": "Claire_Robel@example.net",
								"password": "Holden.Franecki@hotmail.com",
								"created_at": "2022-04-29T05:22:11.771Z"
							}
						},
						{
							"id": 9,
							"content": "cross-platform eco-centric Loan input invoice Avon Cambridgeshire blockchains eyeballs Bacon Handcrafted monitor reinvent Gardens Loan e-enable Re-engineered Orchestrator Engineer Monaco one-to-one Fantastic Albania Visionary Garden withdrawal Upgradable GB Markets deposit",
							"user": {
								"firstname": "Douglas",
								"lastname": "Roob",
								"thumbnail": "https://cdn.fakercloud.com/avatars/xtopherpaul_128.jpg",
								"email": "Trevion_McClure41@example.net",
								"password": "Chadd_Hilpert@gmail.com",
								"created_at": "2022-04-28T11:55:12.401Z"
							}
						},
						{
							"id": 10,
							"content": "withdrawal Awesome up copy ROI Games up Euro Security Forint action-items directional Metal Marketing Gloves microchip Table invoice blue Rustic implement cyan Plastic monitor Organic Hill Multi-tiered Adaptive calculate Loan",
							"user": {
								"firstname": "Ophelia",
								"lastname": "Batz",
								"thumbnail": "https://cdn.fakercloud.com/avatars/andrewofficer_128.jpg",
								"email": "Linnie98@example.net",
								"password": "Linda_Fisher79@hotmail.com",
								"created_at": "2022-04-29T07:33:14.396Z"
							}
						}
					]
				}
			},
			"4": {
				"id": 5,
				"title": "exploit bleeding-edge paradigms",
				"thumbnail": "http://placeimg.com/640/480/people",
				"currentAmount": "32430.53",
				"goalAmount": "100000.00",
				"duration": "2022-09-14T00:36:25.240Z",
				"description": "Front-line global emulation",
				"location": "Reunion",
				"comments": {
					"length": 10,
					"comments": [
						{
							"id": 1,
							"content": "Nicaragua Marshall dot-com Views Tasty synthesize Dynamic magenta Jewelery metrics integrated Auto Montana CSS motivating input Intranet Buckinghamshire Sausages Robust Ameliorated Account streamline drive Berkshire Universal Ergonomic Brazil PCI actuating",
							"user": {
								"firstname": "Melvina",
								"lastname": "Parisian",
								"thumbnail": "https://cdn.fakercloud.com/avatars/evanshajed_128.jpg",
								"email": "Marlene_Christiansen51@example.org",
								"password": "Lillie35@hotmail.com",
								"created_at": "2022-04-29T04:37:16.329Z"
							}
						},
						{
							"id": 2,
							"content": "e-tailers monitor wireless solutions card Plastic Bike Kenyan orange Auto AI Self-enabling Rustic Home Soap target executive Yen cyan Soft Ohio vortals PCI Visionary deposit tan Unbranded Avon Grocery Ergonomic",
							"user": {
								"firstname": "Orland",
								"lastname": "Huel",
								"thumbnail": "https://cdn.fakercloud.com/avatars/fotomagin_128.jpg",
								"email": "Linnie23@example.org",
								"password": "Shea.Schowalter77@yahoo.com",
								"created_at": "2022-04-28T19:36:48.557Z"
							}
						},
						{
							"id": 3,
							"content": "Chair Guadeloupe transmit Myanmar algorithm generating navigating index Berkshire Technician Checking hub Movies Cambridgeshire programming Small Rustic application Generic Account Group transmitter value-added Beauty Optional didactic Buckinghamshire quantify Bike wireless",
							"user": {
								"firstname": "Autumn",
								"lastname": "Farrell",
								"thumbnail": "https://cdn.fakercloud.com/avatars/uxpiper_128.jpg",
								"email": "Brandon87@example.com",
								"password": "Prince.Effertz27@gmail.com",
								"created_at": "2022-04-28T18:53:42.390Z"
							}
						},
						{
							"id": 4,
							"content": "Wooden monitoring Keyboard Plastic framework Implementation generating evolve Games Reunion Steel Ergonomic Dollar Wyoming override haptic withdrawal quantify neural-net Shirt Colorado virtual Franc state open-source encryption Coordinator panel Networked withdrawal",
							"user": {
								"firstname": "Conor",
								"lastname": "Rogahn",
								"thumbnail": "https://cdn.fakercloud.com/avatars/belyaev_rs_128.jpg",
								"email": "Doris47@example.org",
								"password": "Brittany_Wisoky@hotmail.com",
								"created_at": "2022-04-28T16:33:30.330Z"
							}
						},
						{
							"id": 5,
							"content": "Forward SMS Unbranded Maine lavender withdrawal Facilitator withdrawal Progressive web-enabled Refined improvement Jewelery Account Liaison upward-trending Reduced connecting Steel index Gloves Triple-buffered Shilling Afghani Soft Rustic Chips Future neural Peso",
							"user": {
								"firstname": "Yvette",
								"lastname": "Kilback",
								"thumbnail": "https://cdn.fakercloud.com/avatars/brajeshwar_128.jpg",
								"email": "Gilberto_Gaylord@example.com",
								"password": "Laurianne10@yahoo.com",
								"created_at": "2022-04-29T04:58:30.277Z"
							}
						},
						{
							"id": 6,
							"content": "Digitized Sausages Dalasi card Carolina Movies radical e-enable mindshare input French Security Organized Bedfordshire Borders Hat killer Alley cross-platform redundant parse Borders strategy Movies Indiana Frozen Plastic Practical firewall index",
							"user": {
								"firstname": "Nakia",
								"lastname": "Rosenbaum",
								"thumbnail": "https://cdn.fakercloud.com/avatars/iduuck_128.jpg",
								"email": "Garrett29@example.org",
								"password": "Tyrel76@yahoo.com",
								"created_at": "2022-04-28T22:12:11.406Z"
							}
						},
						{
							"id": 7,
							"content": "SMS Intelligent Games green Buckinghamshire Legacy JSON Loan withdrawal invoice artificial Leone virtual end-to-end defect Manat deposit Liaison access Car portals hack Customer SMS Sleek back-end B2B Implemented connect generating",
							"user": {
								"firstname": "Raquel",
								"lastname": "Rohan",
								"thumbnail": "https://cdn.fakercloud.com/avatars/simobenso_128.jpg",
								"email": "Favian45@example.net",
								"password": "Jakayla.Roob37@hotmail.com",
								"created_at": "2022-04-28T21:49:08.752Z"
							}
						},
						{
							"id": 8,
							"content": "Facilitator indexing Account Frozen Universal Ball enable Personal GB digital Computer e-enable Future Cambridgeshire Fresh Product Corporate AI Engineer knowledge Home Direct IB protocol Passage Operations iterate Sleek Central override",
							"user": {
								"firstname": "Luella",
								"lastname": "Yundt",
								"thumbnail": "https://cdn.fakercloud.com/avatars/mtolokonnikov_128.jpg",
								"email": "Felicity_Raynor@example.com",
								"password": "Gina26@yahoo.com",
								"created_at": "2022-04-29T08:48:56.329Z"
							}
						},
						{
							"id": 9,
							"content": "Infrastructure District infomediaries recontextualize Buckinghamshire needs-based Soft program Platinum Tactics wireless Account redefine Horizontal gold Analyst visionary Manat District Internal Dale next implement plum reinvent Money Shirt Manager Ergonomic Direct",
							"user": {
								"firstname": "Katelin",
								"lastname": "Zboncak",
								"thumbnail": "https://cdn.fakercloud.com/avatars/mbilalsiddique1_128.jpg",
								"email": "Alexa_Mueller61@example.org",
								"password": "Everett30@gmail.com",
								"created_at": "2022-04-29T01:19:59.176Z"
							}
						},
						{
							"id": 10,
							"content": "Berkshire Lead Cotton Borders Wooden Berkshire multi-byte Saint Steel capacitor Sausages optical neural Car Solutions Customer Jersey Intranet improvement scalable Colorado program sticky Research Account Dollar Creative complexity violet azure",
							"user": {
								"firstname": "Lois",
								"lastname": "Cassin",
								"thumbnail": "https://cdn.fakercloud.com/avatars/dpmachado_128.jpg",
								"email": "Emma.Funk@example.org",
								"password": "Ewald4@yahoo.com",
								"created_at": "2022-04-29T00:03:13.972Z"
							}
						}
					]
				}
			},
			"5": {
				"id": 6,
				"title": "enhance ubiquitous applications",
				"thumbnail": "http://placeimg.com/640/480/people",
				"currentAmount": "33437.97",
				"goalAmount": "100000.00",
				"duration": "2023-02-16T02:17:40.083Z",
				"description": "Advanced attitude-oriented capacity",
				"location": "Gabon",
				"comments": {
					"length": 10,
					"comments": [
						{
							"id": 1,
							"content": "blockchains alarm experiences black Integration Account withdrawal Human Jewelery synergy Sleek Orchestrator Avon Frozen Israel Romania SDD navigate white Shoes IB withdrawal Generic communities infrastructures Savings bricks-and-clicks Berkshire Shoes Utah",
							"user": {
								"firstname": "Johathan",
								"lastname": "Cremin",
								"thumbnail": "https://cdn.fakercloud.com/avatars/mhaligowski_128.jpg",
								"email": "Vivian55@example.org",
								"password": "Joel.Goldner65@hotmail.com",
								"created_at": "2022-04-28T10:00:33.671Z"
							}
						},
						{
							"id": 2,
							"content": "Buckinghamshire HTTP program Generic Cotton Orchard compress Fully-configurable synthesizing tertiary mission-critical Tuna Automotive secondary Hat solutions interfaces Granite SCSI Peso SSL optimize Buckinghamshire Rubber e-enable Texas Enhanced online magenta Savings",
							"user": {
								"firstname": "Hilario",
								"lastname": "Doyle",
								"thumbnail": "https://cdn.fakercloud.com/avatars/dhooyenga_128.jpg",
								"email": "Gregory_Barrows@example.org",
								"password": "Margaretta68@yahoo.com",
								"created_at": "2022-04-29T01:44:59.024Z"
							}
						},
						{
							"id": 3,
							"content": "24/7 ubiquitous system Bermuda copying auxiliary Chicken XML Practical full-range orange overriding Plastic withdrawal Lats generate withdrawal HDD Unbranded invoice bypassing calculating Assistant Berkshire Bike B2C complexity Ohio Table value-added",
							"user": {
								"firstname": "Terrance",
								"lastname": "Abbott",
								"thumbnail": "https://cdn.fakercloud.com/avatars/laurengray_128.jpg",
								"email": "Hilbert.Nader@example.com",
								"password": "Jeff75@yahoo.com",
								"created_at": "2022-04-28T21:47:16.582Z"
							}
						},
						{
							"id": 4,
							"content": "Loan Shoes invoice Account Data Strategist Sausages Table Colorado Rubber sexy architectures yellow cohesive feed engineer matrix teal Chicken application zero functionalities Functionality full-range Shoes Health applications programming Security wireless",
							"user": {
								"firstname": "Issac",
								"lastname": "Kuphal",
								"thumbnail": "https://cdn.fakercloud.com/avatars/lebinoclard_128.jpg",
								"email": "Ray_Marvin@example.net",
								"password": "Mohammed.Ledner@hotmail.com",
								"created_at": "2022-04-28T16:15:33.242Z"
							}
						},
						{
							"id": 5,
							"content": "Account Ball withdrawal Pants Planner Hills Bacon ADP architectures invoice Customer reboot Shilling projection Dinar tan Intelligent Som web Small Facilitator Bedfordshire morph withdrawal Ngultrum Peso Consultant Washington bluetooth aggregate",
							"user": {
								"firstname": "Erwin",
								"lastname": "Mayer",
								"thumbnail": "https://cdn.fakercloud.com/avatars/robbschiller_128.jpg",
								"email": "Tracey28@example.org",
								"password": "Talia_Kertzmann18@gmail.com",
								"created_at": "2022-04-28T21:18:37.100Z"
							}
						},
						{
							"id": 6,
							"content": "Checking Down-sized Human Haiti user-facing matrix Lithuania communities Shoes bluetooth Chicken Brunei Electronics Reactive 24/7 Iowa SMTP Wall Compatible global Wooden withdrawal Plastic alarm grey connecting Tools Soft intuitive Intranet",
							"user": {
								"firstname": "Keon",
								"lastname": "Littel",
								"thumbnail": "https://cdn.fakercloud.com/avatars/switmer777_128.jpg",
								"email": "Jaeden.Hackett@example.net",
								"password": "Aurelie.Mohr49@yahoo.com",
								"created_at": "2022-04-28T18:47:04.547Z"
							}
						},
						{
							"id": 7,
							"content": "interfaces Colorado Plain Bedfordshire Soap Kansas redefine Baby 5th User-friendly Associate invoice navigating Bacon Regional networks optical end-to-end customized transparent Chief SDD Belgium Aruba synthesize feed Wooden ADP Computer Afghanistan",
							"user": {
								"firstname": "Christop",
								"lastname": "Feil",
								"thumbnail": "https://cdn.fakercloud.com/avatars/daykiine_128.jpg",
								"email": "Kaylin36@example.net",
								"password": "Helen58@hotmail.com",
								"created_at": "2022-04-29T02:40:15.944Z"
							}
						},
						{
							"id": 8,
							"content": "Engineer Lead Cheese Virtual Future withdrawal Garden Hat transition Directives Graphical eyeballs definition Electronics Dynamic Computer Communications payment e-commerce mobile synthesizing out-of-the-box workforce Rubber cross-platform Dong ivory eyeballs Markets end-to-end",
							"user": {
								"firstname": "Tom",
								"lastname": "Krajcik",
								"thumbnail": "https://cdn.fakercloud.com/avatars/mbilderbach_128.jpg",
								"email": "Elvis.Osinski@example.com",
								"password": "Lonzo_Hagenes73@hotmail.com",
								"created_at": "2022-04-29T00:08:30.266Z"
							}
						},
						{
							"id": 9,
							"content": "Chips Optional Plastic Assistant vortals invoice Balboa dynamic Representative Union Rubber Rupee Awesome Buckinghamshire Lek Brand Technician Associate bandwidth-monitored Metal Inverse Marketing sticky archive Computers Wooden Quality task-force granular Massachusetts",
							"user": {
								"firstname": "Jerrold",
								"lastname": "Gleichner",
								"thumbnail": "https://cdn.fakercloud.com/avatars/nelsonjoyce_128.jpg",
								"email": "Jennifer.Hane@example.net",
								"password": "Adan_Kunze@hotmail.com",
								"created_at": "2022-04-29T07:45:08.829Z"
							}
						},
						{
							"id": 10,
							"content": "haptic red Awesome synthesizing XML Dynamic complexity grey vortals strategic cross-platform Handcrafted Loan Libyan overriding program Steel RAM Berkshire Oregon Soap Outdoors deliverables Generic Chips Plaza Cambridgeshire Administrator Garden quantifying",
							"user": {
								"firstname": "Imelda",
								"lastname": "Cronin",
								"thumbnail": "https://cdn.fakercloud.com/avatars/digitalmaverick_128.jpg",
								"email": "Alexandre.Cormier43@example.org",
								"password": "Trinity45@yahoo.com",
								"created_at": "2022-04-29T01:52:06.982Z"
							}
						}
					]
				}
			},
			"6": {
				"id": 7,
				"title": "enhance B2C technologies",
				"thumbnail": "http://placeimg.com/640/480/people",
				"currentAmount": "30394.36",
				"goalAmount": "100000.00",
				"duration": "2023-02-03T17:02:21.472Z",
				"description": "Reactive stable time-frame",
				"location": "Kyrgyz Republic",
				"comments": {
					"length": 10,
					"comments": [
						{
							"id": 1,
							"content": "Bike Congolese Games Automotive asymmetric Games Wooden Bike Investment Wyoming Clothing alliance auxiliary Keyboard Loan workforce forecast Lane contextually-based Tuvalu Plastic Cambridgeshire invoice calculating Customer Gorgeous of Intelligent Tools orchestrate",
							"user": {
								"firstname": "Garnet",
								"lastname": "Lowe",
								"thumbnail": "https://cdn.fakercloud.com/avatars/mattbilotti_128.jpg",
								"email": "Germaine_Von41@example.net",
								"password": "Jedediah_Howe@gmail.com",
								"created_at": "2022-04-28T21:25:36.395Z"
							}
						},
						{
							"id": 2,
							"content": "paradigms redundant Pitcairn Corporate Intelligent bypass evolve Officer Branding withdrawal Horizontal Berkshire AGP deposit Coordinator content-based architectures proactive Account Auto holistic solutions payment invoice Designer Bulgaria Franc architectures Public-key e-services",
							"user": {
								"firstname": "Cole",
								"lastname": "Treutel",
								"thumbnail": "https://cdn.fakercloud.com/avatars/the_winslet_128.jpg",
								"email": "Vince_Conn9@example.org",
								"password": "Jordy60@gmail.com",
								"created_at": "2022-04-28T21:15:34.390Z"
							}
						},
						{
							"id": 3,
							"content": "mobile sexy deposit Account moratorium Grocery Fresh Refined Lodge Peso Configuration Forks Account lavender card Soap Usability Island Bedfordshire leverage override Mississippi Ramp AI Account embrace SAS Circle transmitting Facilitator",
							"user": {
								"firstname": "Angelina",
								"lastname": "Bauch",
								"thumbnail": "https://cdn.fakercloud.com/avatars/michaelcomiskey_128.jpg",
								"email": "Jaclyn64@example.org",
								"password": "Rebeca_Rodriguez@hotmail.com",
								"created_at": "2022-04-28T15:45:24.586Z"
							}
						},
						{
							"id": 4,
							"content": "JSON Isle Fish withdrawal Account Cambridgeshire Gorgeous product Dynamic utilisation EXE withdrawal open-source Accounts Missouri Functionality Mountains Officer Soap Brand solutions Bedfordshire Saint Account withdrawal back invoice Refined Vanuatu Intelligent",
							"user": {
								"firstname": "Francisca",
								"lastname": "Williamson",
								"thumbnail": "https://cdn.fakercloud.com/avatars/nellleo_128.jpg",
								"email": "Rodger10@example.net",
								"password": "Beulah.Reynolds10@gmail.com",
								"created_at": "2022-04-28T17:51:24.320Z"
							}
						},
						{
							"id": 5,
							"content": "teal International calculating Rubber Versatile panel invoice Riel Village calculating Idaho calculate Sleek Coordinator Carolina Stream Managed Incredible leverage Pennsylvania up Tasty Concrete Towels program Practical Philippines Brand FTP blue",
							"user": {
								"firstname": "Ollie",
								"lastname": "Haley",
								"thumbnail": "https://cdn.fakercloud.com/avatars/andyisonline_128.jpg",
								"email": "Danial_Huels@example.net",
								"password": "Korbin_Willms91@yahoo.com",
								"created_at": "2022-04-28T23:39:45.663Z"
							}
						},
						{
							"id": 6,
							"content": "Steel Shoes Grocery hack Frozen navigating executive even-keeled Future Engineer reintermediate transmitter Electronics Savings Kansas orange Expanded lavender Accountability visualize Wyoming parsing Optimized Sports Licensed West Harbor Chicken alarm Honduras",
							"user": {
								"firstname": "Rosalind",
								"lastname": "Conn",
								"thumbnail": "https://cdn.fakercloud.com/avatars/tom_even_128.jpg",
								"email": "Johanna.Mitchell@example.com",
								"password": "Rex_Gislason@gmail.com",
								"created_at": "2022-04-28T11:33:43.325Z"
							}
						},
						{
							"id": 7,
							"content": "ADP metrics Market modular New Rand XML Turnpike Pizza deposit methodologies invoice SMS redundant Cambridgeshire Parks Plastic Arizona web-enabled transmit upward-trending Fish client-driven mesh Granite portals impactful Licensed Plastic Costa",
							"user": {
								"firstname": "Wilson",
								"lastname": "Schroeder",
								"thumbnail": "https://cdn.fakercloud.com/avatars/hota_v_128.jpg",
								"email": "Candace59@example.org",
								"password": "Cassie_Rolfson95@yahoo.com",
								"created_at": "2022-04-29T08:39:27.731Z"
							}
						},
						{
							"id": 8,
							"content": "cross-platform invoice solution-oriented Plastic Jewelery mobile cutting-edge instruction Intelligent Infrastructure Concrete Ruble explicit Islands Beauty Multi-channelled e-markets client-driven infomediaries Concrete Tasty navigating bypass next Convertible Computer Mouse Belgium Colorado driver",
							"user": {
								"firstname": "Felix",
								"lastname": "Bauch",
								"thumbnail": "https://cdn.fakercloud.com/avatars/aislinnkelly_128.jpg",
								"email": "Demetris66@example.com",
								"password": "Stephan_Abbott@gmail.com",
								"created_at": "2022-04-28T17:42:54.265Z"
							}
						},
						{
							"id": 9,
							"content": "Cotton calculate invoice Bedfordshire target Supervisor distributed transmitting client-driven Liaison Tasty array parsing Road Burg synthesizing Antillian Virginia Gloves Denar deposit bandwidth interface connecting ADP orchid array back-end communities Account",
							"user": {
								"firstname": "Jimmy",
								"lastname": "Labadie",
								"thumbnail": "https://cdn.fakercloud.com/avatars/sterlingrules_128.jpg",
								"email": "Laurine.Rolfson38@example.net",
								"password": "Stevie_Pollich0@hotmail.com",
								"created_at": "2022-04-28T17:38:19.474Z"
							}
						},
						{
							"id": 10,
							"content": "Rial Missouri workforce override Refined bluetooth firmware Dam methodical Metal navigating circuit Washington open bandwidth Soft portals intuitive Cotton Fresh Peru Investment monitor Idaho Palladium magnetic Unbranded Concrete Front-line withdrawal",
							"user": {
								"firstname": "Domenica",
								"lastname": "Lind",
								"thumbnail": "https://cdn.fakercloud.com/avatars/abdullindenis_128.jpg",
								"email": "Horacio_Gutkowski23@example.net",
								"password": "Lance_Terry59@gmail.com",
								"created_at": "2022-04-28T10:03:42.274Z"
							}
						}
					]
				}
			},
			"7": {
				"id": 8,
				"title": "embrace synergistic e-tailers",
				"thumbnail": "http://placeimg.com/640/480/people",
				"currentAmount": "21971.18",
				"goalAmount": "100000.00",
				"duration": "2023-03-19T01:57:56.018Z",
				"description": "Integrated leading edge firmware",
				"location": "Macao",
				"comments": {
					"length": 10,
					"comments": [
						{
							"id": 1,
							"content": "invoice Hill orchid Concrete vortals generate repurpose yellow Cambridgeshire Chair Automotive SDD withdrawal infrastructures Consultant Somalia Car Chief fresh-thinking orchestrate Small matrices Avon reintermediate Product Strategist calculating Seamless calculating Path",
							"user": {
								"firstname": "Rebekah",
								"lastname": "Willms",
								"thumbnail": "https://cdn.fakercloud.com/avatars/tobysaxon_128.jpg",
								"email": "Declan.Nitzsche@example.com",
								"password": "Dustin11@gmail.com",
								"created_at": "2022-04-29T09:43:48.535Z"
							}
						},
						{
							"id": 2,
							"content": "Health Shilling violet SMTP Ergonomic Rustic Pizza bifurcated Facilitator Avon Rubber Chief Pants intermediate Web payment bluetooth Administrator Vista PCI Health payment North copying evolve Sausages Savings Villages revolutionary ability",
							"user": {
								"firstname": "Laila",
								"lastname": "Miller",
								"thumbnail": "https://cdn.fakercloud.com/avatars/salimianoff_128.jpg",
								"email": "Melyssa57@example.com",
								"password": "Angelina_Fisher76@gmail.com",
								"created_at": "2022-04-28T11:32:14.939Z"
							}
						},
						{
							"id": 3,
							"content": "Facilitator bypassing indexing Valleys Gloves system Intelligent Arizona connect infrastructure functionalities indigo Identity redundant Central input payment THX efficient Tasty Street clicks-and-mortar Data GB functionalities harness Rubber deposit invoice Minnesota",
							"user": {
								"firstname": "Chester",
								"lastname": "Morar",
								"thumbnail": "https://cdn.fakercloud.com/avatars/funwatercat_128.jpg",
								"email": "Ernest23@example.org",
								"password": "Mohamed.Bechtelar@yahoo.com",
								"created_at": "2022-04-28T12:04:49.058Z"
							}
						},
						{
							"id": 4,
							"content": "Concrete Ohio Cambridgeshire hack Ports Buckinghamshire Garden interactive Metrics Philippine Dynamic Sausages Lari lime Taka capability violet mobile alarm cultivate programming lime Plaza Administrator Account Kids Ghana driver parsing systems",
							"user": {
								"firstname": "Richie",
								"lastname": "Smith",
								"thumbnail": "https://cdn.fakercloud.com/avatars/dreizle_128.jpg",
								"email": "Quinton56@example.net",
								"password": "Roscoe.Dietrich58@gmail.com",
								"created_at": "2022-04-29T08:10:26.413Z"
							}
						},
						{
							"id": 5,
							"content": "cross-platform Chicken parsing 5th e-commerce Plastic Hat services EXE 1080p Fantastic Incredible Manager Ergonomic compress Jewelery Table solution-oriented encryption Investment mobile Synergistic Intelligent state target Music Mouse Program cross-platform compress",
							"user": {
								"firstname": "Alphonso",
								"lastname": "Jast",
								"thumbnail": "https://cdn.fakercloud.com/avatars/joshhemsley_128.jpg",
								"email": "Queenie_Renner@example.com",
								"password": "Mckenzie14@gmail.com",
								"created_at": "2022-04-29T02:34:43.389Z"
							}
						},
						{
							"id": 6,
							"content": "salmon Buckinghamshire collaborative navigate Roads markets Freeway Computer capacitor generate groupware Ergonomic Global sensor supply-chains Direct vortals applications overriding Mountains driver Designer driver Tuna Seychelles Architect digital Rico Harbors Oregon",
							"user": {
								"firstname": "Erwin",
								"lastname": "Farrell",
								"thumbnail": "https://cdn.fakercloud.com/avatars/tbakdesigns_128.jpg",
								"email": "Adelia8@example.org",
								"password": "Wayne44@gmail.com",
								"created_at": "2022-04-28T21:39:29.476Z"
							}
						},
						{
							"id": 7,
							"content": "Bahamian Account platforms Frozen Paraguay Profound copy Devolved Car generate Virginia override mindshare Function-based Industrial Berkshire 1080p systems deposit Wooden Shilling Money streamline Borders indexing parse Industrial best-of-breed optical Music",
							"user": {
								"firstname": "Willy",
								"lastname": "Prosacco",
								"thumbnail": "https://cdn.fakercloud.com/avatars/stan_128.jpg",
								"email": "Anais87@example.com",
								"password": "Eliseo.Kulas43@gmail.com",
								"created_at": "2022-04-29T02:35:31.802Z"
							}
						},
						{
							"id": 8,
							"content": "Chair Money bypassing Quality HDD virtual alarm Sports Dinar Alley Tasty Alaska holistic synergize orchid Dirham Supervisor Incredible wireless Mobility Bike Hawaii Car Ohio engineer Krone initiatives portals Corporate Bike",
							"user": {
								"firstname": "Zetta",
								"lastname": "Wiza",
								"thumbnail": "https://cdn.fakercloud.com/avatars/imsoper_128.jpg",
								"email": "Doyle.Morar@example.org",
								"password": "Rodrick.Nader@hotmail.com",
								"created_at": "2022-04-29T02:16:41.557Z"
							}
						},
						{
							"id": 9,
							"content": "Guarani neural back-end Integration Jersey auxiliary Chief quantify deposit Chips infrastructures metrics Assistant Mobility Garden calculate Pants Colon Sleek process platforms Chicken Gorgeous embrace syndicate efficient Assurance e-tailers Sausages Chips",
							"user": {
								"firstname": "Clark",
								"lastname": "Stracke",
								"thumbnail": "https://cdn.fakercloud.com/avatars/primozcigler_128.jpg",
								"email": "Rodger.Steuber@example.org",
								"password": "Jonathon.Yost@hotmail.com",
								"created_at": "2022-04-28T19:00:52.965Z"
							}
						},
						{
							"id": 10,
							"content": "transmitting alliance Salad Arkansas Baby Massachusetts monitor utilize 4th capacitor granular XSS Virtual User-friendly optimize Outdoors Assistant payment CSS Devolved Markets Factors Dynamic deposit Jewelery Clothing Michigan SQL navigate bottom-line",
							"user": {
								"firstname": "Hilton",
								"lastname": "Littel",
								"thumbnail": "https://cdn.fakercloud.com/avatars/vanchesz_128.jpg",
								"email": "Magnolia.Kohler81@example.com",
								"password": "Arvel38@gmail.com",
								"created_at": "2022-04-28T23:23:08.853Z"
							}
						}
					]
				}
			},
			"8": {
				"id": 9,
				"title": "benchmark leading-edge paradigms",
				"thumbnail": "http://placeimg.com/640/480/people",
				"currentAmount": "36815.74",
				"goalAmount": "100000.00",
				"duration": "2022-08-04T22:55:40.884Z",
				"description": "Distributed analyzing process improvement",
				"location": "Monaco",
				"comments": {
					"length": 10,
					"comments": [
						{
							"id": 1,
							"content": "invoice Berkshire Buckinghamshire Manager communities Supervisor SQL SCSI blue salmon Yemen Granite Loan Small lavender calculating Yen Principal Intranet bus Pike Greenland Identity deploy brand intuitive Cross-platform installation Paradigm monitor",
							"user": {
								"firstname": "Cecil",
								"lastname": "Fadel",
								"thumbnail": "https://cdn.fakercloud.com/avatars/besbujupi_128.jpg",
								"email": "Arlie.Schiller@example.com",
								"password": "Nedra2@hotmail.com",
								"created_at": "2022-04-29T07:37:39.282Z"
							}
						},
						{
							"id": 2,
							"content": "infomediaries microchip Kids Illinois toolset ubiquitous cross-media connecting hardware Expressway RAM Square Cotton Granite Sri Shoes Soft end-to-end Fantastic exuding maroon Outdoors calculating Tuna transmitter redefine indexing Direct Vietnam Liaison",
							"user": {
								"firstname": "Charlie",
								"lastname": "Kunde",
								"thumbnail": "https://cdn.fakercloud.com/avatars/dorphern_128.jpg",
								"email": "Johanna.Rowe@example.org",
								"password": "Domenica_Hilpert88@gmail.com",
								"created_at": "2022-04-28T16:16:07.096Z"
							}
						},
						{
							"id": 3,
							"content": "facilitate bypassing Central Granite Computer Sausages Inlet Incredible hard JSON Buckinghamshire Barbados Product District Diverse Plain Lead 3rd Pennsylvania parsing Kroon digital Sleek Chief Handmade International global improvement override South",
							"user": {
								"firstname": "Giles",
								"lastname": "Casper",
								"thumbnail": "https://cdn.fakercloud.com/avatars/felipecsl_128.jpg",
								"email": "Amara_Swift@example.net",
								"password": "Amiya_Volkman@hotmail.com",
								"created_at": "2022-04-28T23:53:15.978Z"
							}
						},
						{
							"id": 4,
							"content": "Fundamental Soft Tuvalu Forge Right-sized Practical Frozen multi-byte Granite evolve Assistant turquoise drive Architect virtual Metal Table Cambridgeshire digital Idaho Brand Sum SMS optical up withdrawal bypass Metal Crest Dinar",
							"user": {
								"firstname": "Jamar",
								"lastname": "Fadel",
								"thumbnail": "https://cdn.fakercloud.com/avatars/daykiine_128.jpg",
								"email": "Nayeli.Balistreri0@example.org",
								"password": "Coralie_Hammes23@yahoo.com",
								"created_at": "2022-04-28T13:11:49.308Z"
							}
						},
						{
							"id": 5,
							"content": "Minnesota iterate mindshare Guarani mobile Investment Franc Sports Web hack Soft panel Lead Generic Libyan Metal bandwidth Brunei Car turquoise Small Hat Executive driver Buckinghamshire Greens content Account Executive Versatile",
							"user": {
								"firstname": "Glen",
								"lastname": "Metz",
								"thumbnail": "https://cdn.fakercloud.com/avatars/ChrisFarina78_128.jpg",
								"email": "Dagmar.Simonis@example.com",
								"password": "Delaney.Kuphal4@hotmail.com",
								"created_at": "2022-04-29T01:34:46.722Z"
							}
						},
						{
							"id": 6,
							"content": "Reduced invoice deposit Rubber Senior AI customized compressing integrated modular Universal Tuna Steel e-commerce group Fantastic Martinique architectures Ergonomic Tuna Macedonia Manager Market PCI Squares Island Branding flexibility copying Soft",
							"user": {
								"firstname": "Kristian",
								"lastname": "Tillman",
								"thumbnail": "https://cdn.fakercloud.com/avatars/uxalex_128.jpg",
								"email": "Rachelle.Bartell@example.com",
								"password": "Ernie_Brown@yahoo.com",
								"created_at": "2022-04-29T06:52:09.272Z"
							}
						},
						{
							"id": 7,
							"content": "Assistant Berkshire payment Grocery cross-platform magnetic foreground Poland Savings mission-critical transition red Investment Zimbabwe Lead payment Practical web Oklahoma firewall Multi-lateral viral Granite 3rd Gibraltar GB Drives revolutionize Macao synthesize",
							"user": {
								"firstname": "Jovani",
								"lastname": "Roob",
								"thumbnail": "https://cdn.fakercloud.com/avatars/dimaposnyy_128.jpg",
								"email": "Daphnee.Grady@example.org",
								"password": "Hassan36@hotmail.com",
								"created_at": "2022-04-28T23:45:32.198Z"
							}
						},
						{
							"id": 8,
							"content": "Pants parse primary access Wooden Optimization Music interactive XSS Decentralized Arkansas payment wireless Bike quantifying Wooden Avon Inverse Leu portal frictionless PCI Colorado Bedfordshire generating Producer Outdoors Soap client-server Buckinghamshire",
							"user": {
								"firstname": "Ethyl",
								"lastname": "King",
								"thumbnail": "https://cdn.fakercloud.com/avatars/saarabpreet_128.jpg",
								"email": "Salvatore19@example.org",
								"password": "Queen_Stiedemann@hotmail.com",
								"created_at": "2022-04-28T19:03:15.413Z"
							}
						},
						{
							"id": 9,
							"content": "generate Fish multi-tasking Berkshire Dollar Rustic portals Representative Infrastructure and Lek Clothing real-time JSON payment Computers Implementation impactful Fresh Coordinator Rufiyaa Buckinghamshire withdrawal Progressive back-end Soap Mill Awesome Mouse Shoes",
							"user": {
								"firstname": "Ephraim",
								"lastname": "Emard",
								"thumbnail": "https://cdn.fakercloud.com/avatars/pcridesagain_128.jpg",
								"email": "Lee_Rohan44@example.org",
								"password": "Danny.Mertz@hotmail.com",
								"created_at": "2022-04-29T09:23:29.506Z"
							}
						},
						{
							"id": 10,
							"content": "Tuna Bolivia Jewelery Kids PCI Lead Face Massachusetts Gorgeous Maine SMTP protocol moratorium port Credit hacking Synergistic Bahamas Borders calculate Wooden Lead FTP Account tertiary disintermediate Administrator Account program Division",
							"user": {
								"firstname": "Lizzie",
								"lastname": "Daugherty",
								"thumbnail": "https://cdn.fakercloud.com/avatars/instalox_128.jpg",
								"email": "Laron17@example.net",
								"password": "Carlo.Kuhn@gmail.com",
								"created_at": "2022-04-29T09:27:11.337Z"
							}
						}
					]
				}
			},
			"9": {
				"id": 10,
				"title": "drive extensible paradigms",
				"thumbnail": "http://placeimg.com/640/480/people",
				"currentAmount": "23017.11",
				"goalAmount": "100000.00",
				"duration": "2023-02-05T02:52:17.534Z",
				"description": "Function-based modular Graphical User Interface",
				"location": "Grenada",
				"comments": {
					"length": 10,
					"comments": [
						{
							"id": 1,
							"content": "Rustic Buckinghamshire payment Saudi Infrastructure Producer calculate Cotton database withdrawal red invoice infrastructures invoice analyzing Trafficway payment Freeway Wooden wireless compelling quantifying Future bypass Bedfordshire solid Engineer deliverables Burg proactive",
							"user": {
								"firstname": "Jacynthe",
								"lastname": "Towne",
								"thumbnail": "https://cdn.fakercloud.com/avatars/danvernon_128.jpg",
								"email": "Sheila_Ebert@example.org",
								"password": "Filiberto.Dietrich79@gmail.com",
								"created_at": "2022-04-28T20:08:24.717Z"
							}
						},
						{
							"id": 2,
							"content": "Island Won Jewelery grey Industrial quantifying Lead cross-media Dynamic Division Movies Grocery object-oriented Plaza generate Internal Cambridgeshire Cliff Refined Macao calculating Account Chair extend transition channels Product haptic Multi-channelled Islands",
							"user": {
								"firstname": "Kari",
								"lastname": "Nolan",
								"thumbnail": "https://cdn.fakercloud.com/avatars/oskamaya_128.jpg",
								"email": "Aurelie_Zieme64@example.org",
								"password": "Raven_Jenkins@gmail.com",
								"created_at": "2022-04-28T22:08:44.633Z"
							}
						},
						{
							"id": 3,
							"content": "parse group Representative SSL Tasty Qatari Refined Cambridgeshire Music Account Cambridgeshire Towels Programmable virtual Buckinghamshire bluetooth Rubber SMS Bacon Dynamic Down-sized 24/7 1080p Human Officer transmitter Sheqel e-commerce Rustic Car",
							"user": {
								"firstname": "Hollis",
								"lastname": "Cummerata",
								"thumbnail": "https://cdn.fakercloud.com/avatars/agromov_128.jpg",
								"email": "Lane.Runolfsdottir@example.com",
								"password": "Warren_Rippin@hotmail.com",
								"created_at": "2022-04-29T02:18:13.084Z"
							}
						},
						{
							"id": 4,
							"content": "Product Awesome benchmark Loan Dalasi Chair hack Island deliverables Savings alliance e-business Producer transmit International invoice International Berkshire redundant withdrawal Beauty capacitor Small Sleek Dynamic Refined National transmit RAM transmit",
							"user": {
								"firstname": "Tevin",
								"lastname": "Hane",
								"thumbnail": "https://cdn.fakercloud.com/avatars/chris_frees_128.jpg",
								"email": "Gail_Kirlin@example.net",
								"password": "Rusty17@hotmail.com",
								"created_at": "2022-04-28T11:32:58.809Z"
							}
						},
						{
							"id": 5,
							"content": "overriding gold Loan capacitor User-centric Dinar Pizza invoice open-source Berkshire Practical Cotton invoice IB Route Solutions hard Supervisor payment empower transmitting neural Arizona reboot Analyst Account Senior motivating Berkshire Tactics",
							"user": {
								"firstname": "Tianna",
								"lastname": "Rogahn",
								"thumbnail": "https://cdn.fakercloud.com/avatars/stevedesigner_128.jpg",
								"email": "Misael.Hickle@example.net",
								"password": "Lukas_Haag@yahoo.com",
								"created_at": "2022-04-28T23:25:11.862Z"
							}
						},
						{
							"id": 6,
							"content": "web-enabled Berkshire Wooden hacking PCI Avon port Cambridgeshire cross-media Bedfordshire circuit Palladium Investment conglomeration Chair cross-media service-desk Brazilian payment deliverables Towels Argentina Sleek Arkansas Nepalese Interactions Decentralized architectures Venezuela Investor",
							"user": {
								"firstname": "Kaleigh",
								"lastname": "West",
								"thumbnail": "https://cdn.fakercloud.com/avatars/sulaqo_128.jpg",
								"email": "Kieran48@example.com",
								"password": "Alvis37@yahoo.com",
								"created_at": "2022-04-29T06:42:28.405Z"
							}
						},
						{
							"id": 7,
							"content": "black Plains Tactics Car Reverse-engineered end-to-end Principal Fish Leone Factors Turnpike engage Research Shoes discrete Tools integrate cross-platform override Awesome Borders Generic yellow EXE violet Buckinghamshire Shoes optical purple Sleek",
							"user": {
								"firstname": "Jody",
								"lastname": "Miller",
								"thumbnail": "https://cdn.fakercloud.com/avatars/cadikkara_128.jpg",
								"email": "April_Cartwright@example.net",
								"password": "Lela_Marvin48@hotmail.com",
								"created_at": "2022-04-28T18:01:52.642Z"
							}
						},
						{
							"id": 8,
							"content": "Kids sensor Chips e-business approach monitor Refined Supervisor Samoa expedite bandwidth bypass deploy redundant Lilangeni Personal Pants Toys transition Account Electronics Enhanced Washington Account Overpass Fresh virtual Rhode mobile panel",
							"user": {
								"firstname": "Shanny",
								"lastname": "Greenfelder",
								"thumbnail": "https://cdn.fakercloud.com/avatars/artvavs_128.jpg",
								"email": "Stan68@example.net",
								"password": "Jarod_Balistreri91@hotmail.com",
								"created_at": "2022-04-28T14:07:06.064Z"
							}
						},
						{
							"id": 9,
							"content": "cross-media Monitored Motorway lime Mauritius Computers Account Beauty Japan Horizontal Program withdrawal Unbranded scalable Tools vortals hard Music grey California Account orchestrate Indiana Representative Stream Industrial payment distributed e-services encoding",
							"user": {
								"firstname": "Betsy",
								"lastname": "Bednar",
								"thumbnail": "https://cdn.fakercloud.com/avatars/anatolinicolae_128.jpg",
								"email": "Dalton.Becker@example.com",
								"password": "Carolanne26@hotmail.com",
								"created_at": "2022-04-29T05:36:35.334Z"
							}
						},
						{
							"id": 10,
							"content": "Incredible National Associate solutions Cheese pink Forward Digitized Cheese array Cotton microchip Regional Streets copy Grocery incubate green connect Fantastic Creative Missouri invoice model Bedfordshire hacking empowering withdrawal Small Horizontal",
							"user": {
								"firstname": "Giovanny",
								"lastname": "Stehr",
								"thumbnail": "https://cdn.fakercloud.com/avatars/betraydan_128.jpg",
								"email": "Karine.Hilpert@example.com",
								"password": "Tyrique.Adams@gmail.com",
								"created_at": "2022-04-29T02:29:13.928Z"
							}
						}
					]
				}
			}
		}
	}
}